[
  {"category": "INTERNET", "question": "Jaki dźwięk towarzyszył łączeniu się z internetem przez modem przed erą Neostrady?", "answers": ["Brak dźwięku", "Krótkie pikanie", "Słynny pisk i szum (Dial-up)", "Głos lektora 'Łączę'"], "correct": 2},
  {"category": "KOMUNIKATORY", "question": "Jaki status w Gadu-Gadu miał ikonkę słoneczka z chmurką?", "answers": ["Dostępny", "Zaraz wracam", "Niewidoczny", "Niedostępny"], "correct": 1},
  {"category": "TV", "question": "Kto prowadził kultowy program 'Idol' w Polsacie?", "answers": ["Kuba Wojewódzki", "Maciej Rock", "Krzysztof Ibisz", "Hubert Urbański"], "correct": 1},
  {"category": "MUZYKA", "question": "Która wokalistka wydała w 2002 roku album 'Skrrt', chociaż tak naprawdę album z hitem 'Complicated' nazywał się 'Let Go'?", "answers": ["Britney Spears", "Avril Lavigne", "Pink", "Christina Aguilera"], "correct": 1},
  {"category": "FILM", "question": "W którym roku odbyła się premiera pierwszej części 'Władcy Pierścieni: Drużyna Pierścienia'?", "answers": ["1999", "2000", "2001", "2003"], "correct": 2},
  {"category": "GADŻETY", "question": "Co to był Tamagotchi?", "answers": ["Konsola przenośna Nintendo", "Wirtualny zwierzak", "Rodzaj dzwonka polifonicznego", "Odtwarzacz MP3"], "correct": 1},
  {"category": "GRY", "question": "Jaka mapa w Counter-Strike 1.6 z dwiema wieżami snajperskimi i długim mostem była absolutnym klasykiem w kafejkach internetowych?", "answers": ["de_dust2", "cs_assault", "awp_india", "de_aztec"], "correct": 3},
  {"category": "SPORT", "question": "W którym roku Adam Małysz wygrał swój pierwszy Turniej Czterech Skoczni, rozpoczynając Małyszomanię?", "answers": ["1999/2000", "2000/2001", "2001/2002", "2002/2003"], "correct": 1},
  {"category": "MUZYKA PL", "question": "Jak miał na imię wokalista zespołu Ich Troje, z którym zespół reprezentował Polskę na Eurowizji 2003?", "answers": ["Piotr", "Michał", "Jacek", "Tomasz"], "correct": 1},
  {"category": "TELEFONY", "question": "Jaka firma zdominowała rynek telefonów komórkowych na początku lat 2000 m.in. modelami 3310 czy 3210?", "answers": ["Motorola", "Siemens", "Nokia", "Sony Ericsson"], "correct": 2},
  {"category": "INTERNET PL", "question": "Jaka polska strona internetowa pozwalała na ocenianie zdjęć innych internautów od 1 do 10?", "answers": ["Grono.net", "Nasza Klasa", "Fotka.pl", "E-Puls"], "correct": 2},
  {"category": "MODA", "question": "Jaki typ spodni święcił triumfy wśród kobiet na początku lat zerowych (często w parze z wystającymi stringami)?", "answers": ["Dzwony z wysokim stanem", "Biodrówki", "Rurki", "Dresy ortalionowe"], "correct": 1},
  {"category": "MUZYKA", "question": "Kto śpiewał hit 'Toxic' z 2003 roku?", "answers": ["Madonna", "Kylie Minogue", "Britney Spears", "Gwen Stefani"], "correct": 2},
  {"category": "CZASOPISMA", "question": "Z jakiego czasopisma młodzieżowego najczęściej wyrywało się plakaty na ścianę?", "answers": ["Kaczor Donald", "Bravo", "Popcorn", "Twój Styl"], "correct": 1},
  {"category": "POLITYKA", "question": "W którym roku Polska weszła do Unii Europejskiej?", "answers": ["2002", "2003", "2004", "2005"], "correct": 2},
  {"category": "TV PL", "question": "Jak nazywał się serial animowany o hydrauliku i jego rodzinie emitowany na Polsacie?", "answers": ["Świat według Kiepskich", "Włatcy Móch", "Blok Ekipa", "Kapitan Bomba"], "correct": 1},
  {"category": "TECHNOLOGIA", "question": "Jaki program P2P służył najczęściej do nielegalnego pobierania mp3 (i miał ikonkę z limonką)?", "answers": ["eMule", "KaZaA", "LimeWire", "Ares"], "correct": 2},
  {"category": "FILM PL", "question": "Z jakiego polskiego filmu pochodzi cytat 'Koko dżambo i do przodu'?", "answers": ["Kiler", "Chłopaki nie płaczą", "Poranek kojota", "Czas surferów"], "correct": 1},
  {"category": "TV", "question": "Jak nazywała się prezenterka i gwiazda 'Baru', która wydała album 'Mandaryna.com'?", "answers": ["Doda", "Maja Frykowska", "Marta Wiśniewska", "Agnieszka Frykowska"], "correct": 2},
  {"category": "GRY", "question": "Jak nazywał się kod na nieskończone pieniądze (50 000 simoleonów) w The Sims 1?", "answers": ["rosebud", "motherlode", "klapaucius", "kaching"], "correct": 0},
  {"category": "INTERNET", "question": "Jaka przeglądarka internetowa dominowała absolutnie przed powstaniem Firefoxa i Chrome'a?", "answers": ["Netscape Navigator", "Opera", "Internet Explorer", "Safari"], "correct": 2},
  {"category": "SPORT", "question": "Gdzie odbyły się Mistrzostwa Świata w Piłce Nożnej w 2002 roku, na których zagrała Polska?", "answers": ["Niemcy", "Francja", "Korea Południowa i Japonia", "RPA"], "correct": 2},
  {"category": "MUZYKA PL", "question": "Który polski raper wydał w 2001 roku głośną płytę 'Kinol'?", "answers": ["Peja", "Tede", "Liroy", "O.S.T.R."], "correct": 1},
  {"category": "TV PL", "question": "Kto wygrał pierwszą polską edycję 'Tańca z Gwiazdami' (w TVN)?", "answers": ["Katarzyna Cichopek", "Olivier Janiak", "Rafał Mroczek", "Kinga Rusin"], "correct": 1},
  {"category": "GADŻETY", "question": "Jaki odtwarzacz muzyczny zrewolucjonizował rynek w 2001 roku dzięki pojemności '1000 piosenek w Twojej kieszeni'?", "answers": ["Walkman Sony", "Discman", "Apple iPod", "Creative Zen"], "correct": 2},
  {"category": "FILM", "question": "Jaką pigułkę wybrał Neo w filmie 'Matrix'?", "answers": ["Niebieską", "Czerwoną", "Zieloną", "Żółtą"], "correct": 1},
  {"category": "INTERNET PL", "question": "Jaki portal służył jako wczesna społecznościówka dla 'elity', do której trzeba było dostać zaproszenie od znajomego?", "answers": ["E-Puls", "Nasza Klasa", "Grono.net", "GoldenLine"], "correct": 2},
  {"category": "TV", "question": "Z jakiego programu pochodzi kultowe zawołanie 'Cześć i czołem, kluski z rosołem!'?", "answers": ["Hugo", "Domowe Przedszkole", "Rower Błażeja", "Teleranek"], "correct": 0},
  {"category": "MUZYKA", "question": "Kto śpiewał 'Dragostea Din Tei' (znane jako 'Numa Numa')?", "answers": ["O-Zone", "Tatu", "Las Ketchup", "Crazy Frog"], "correct": 0},
  {"category": "KOMUNIKATORY", "question": "Co wpisywało się w opis GG, gdy chciało się pokazać, że ma się doła?", "answers": ["Wiersz Szymborskiej", "Cytaty z piosenek Myslovitz lub Paktofoniki", "Zwykłe 'Smutno mi'", "Znaczek :( "], "correct": 1},
  {"category": "MODA", "question": "Jak nazywały się buty na bardzo grubej, gumowej platformie (często noszone przez Spice Girls, modne jeszcze na początku lat zerowych)?", "answers": ["Emu", "Glany", "Buffalo", "Crocsy"], "correct": 2},
  {"category": "TV PL", "question": "Jak nazywał się teleturniej prowadzony przez Karola Strasburgera, w którym 'więcej niż jedno zwierzę' to...?", "answers": ["Koło Fortuny", "Jeden z dziesięciu", "Awantura o kasę", "Familiada"], "correct": 3},
  {"category": "GRY", "question": "W jakiej grze z 2004 roku gracz wcielał się w Carla 'CJ' Johnsona?", "answers": ["Mafia", "GTA: Vice City", "GTA: San Andreas", "Need for Speed: Underground"], "correct": 2},
  {"category": "MUZYKA PL", "question": "Która wokalistka śpiewała 'Dżaga' z zespołem Virgin?", "answers": ["Ewelina Flinta", "Doda", "Kasia Kowalska", "Agnieszka Chylińska"], "correct": 1},
  {"category": "FILM PL", "question": "W jakim filmie z 2002 r. Marek Kondrat gra sfrustrowanego polonistę Adasia Miauczyńskiego?", "answers": ["Dzień Świra", "Wszyscy jesteśmy Chrystusami", "Nic śmiesznego", "Psy"], "correct": 0},
  {"category": "INTERNET", "question": "Jaki serwis z wideo powstał w 2005 roku, a pierwszym filmem było 'Me at the zoo'?", "answers": ["Vimeo", "Dailymotion", "YouTube", "Smosh"], "correct": 2},
  {"category": "TV PL", "question": "Jak nazywał się program, w którym Michał Wiśniewski szukał wokalistki do Ich Troje?", "answers": ["Idol", "Droga do Gwiazd", "Jestem Jaki Jestem", "Szansa na Sukces"], "correct": 2},
  {"category": "MUZYKA", "question": "Jaka 'Szalona Żaba' opanowała dzwonki polifoniczne w 2005 roku swoim remiksem 'Axel F'?", "answers": ["Gummy Bear", "Crazy Frog", "Schnappi", "DJ Alligator"], "correct": 1},
  {"category": "CZASOPISMA", "question": "Jaki magazyn o grach dorzucał pełniaki na płytach CD/DVD i miał na okładce żółtego uśmieszka (Smugglera)?", "answers": ["Click!", "Play", "Cyber Mycha", "CD-Action"], "correct": 3},
  {"category": "TV", "question": "Kto był pierwszym prowadzącym program 'Milionerzy'?", "answers": ["Krzysztof Ibisz", "Hubert Urbański", "Zygmunt Chajzer", "Piotr Gąsowski"], "correct": 1},
  {"category": "GADŻETY", "question": "Jak nazywał się nośnik pamięci, który przed pendrive'ami mieścił całe 1.44 MB danych?", "answers": ["Płyta CD", "Dyskietka", "Karta SD", "Kaseta VHS"], "correct": 1},
  {"category": "MUZYKA PL", "question": "Jaki zespół założyli bracia Waglewscy (Fisz i Emade) pod koniec lat 90., co ukształtowało hip-hop lat zerowych?", "answers": ["Kaliber 44", "Paktofonika", "RHX", "Grammatik"], "correct": 2},
  {"category": "INTERNET", "question": "Jak nazywała się najpopularniejsza wczesna usługa poczty e-mail i portalu od Wirtualnej Polski?", "answers": ["Onet", "Interia", "WP", "Tlen"], "correct": 2},
  {"category": "MODA", "question": "Co to były 'frotki' na rękach, które nosili często fani punk-rocka i Avril Lavigne?", "answers": ["Kolorowe gumki do włosów noszone na nadgarstku", "Skórzane bransolety z ćwiekami", "Opaski pochłaniające pot", "Plecionki z muliny"], "correct": 2},
  {"category": "FILM", "question": "Jak nazywa się ryba, której ojciec przemierza ocean w hicie Pixara z 2003 roku?", "answers": ["Dory", "Marlin", "Nemo", "Bruce"], "correct": 2},
  {"category": "TV PL", "question": "Kto krzyczał 'Zonk!' w teleturnieju 'Idź na całość' na Polsacie (wczesne lata 2000)?", "answers": ["Zygmunt Chajzer", "Krzysztof Ibisz", "Kamil Durczok", "Maciej Orłoś"], "correct": 0},
  {"category": "MUZYKA", "question": "Jaki zespół nu-metalowy nagrał kultowy album 'Meteora' w 2003 roku?", "answers": ["Limp Bizkit", "Korn", "System of a Down", "Linkin Park"], "correct": 3},
  {"category": "KOMUNIKATORY", "question": "Jaki program, oprócz GG, zyskał w Polsce popularność dzięki możliwości odbierania poczty o2.pl?", "answers": ["Skype", "Tlen.pl", "ICQ", "AQQ"], "correct": 1},
  {"category": "GRY", "question": "Jak się nazywa wirtualna symulacja życia (często ustawiana na NK czy Gronie jako gra przeglądarkowa)?", "answers": ["Ogame", "Plemiona", "Second Life", "Margonem"], "correct": 1},
  {"category": "MUZYKA PL", "question": "Z jakiego utworu Kasi Klich pochodzi fraza 'Lepszy rydz niż nic' (2002)?", "answers": ["Będę robić nic", "Lepszy model", "Piesku mały", "Życie cudem jest"], "correct": 1},
  {"category": "TV PL", "question": "Kto wygrał pierwszą, historyczną polską edycję 'Big Brothera' w 2001 roku?", "answers": ["Klaudiusz Ševković", "Janusz Dzięcioł", "Piotr 'Gulczas' Gulczyński", "Manuela Michalak"], "correct": 1},
  {"category": "INTERNET PL", "question": "Jak nazywał się wprowadzony w 2009 roku na Naszej Klasie mikroblog, który wywołał falę protestów i łańcuszków domagających się jego usunięcia?", "answers": ["Śledzik", "Pikaczu", "Blok Ekipa", "Gadu-Gadu"], "correct": 0},
  {"category": "MUZYKA PL", "question": "Jaki polski utwór hip-hopolo zaczynał się od słów 'Ile dałbym, by zapomnieć Cię...' (2003)?", "answers": ["Mezo - Ważne", "Jeden Osiem L - Jak zapomnieć", "Verba - Młode Wilki", "Ascetoholix - Suczki"], "correct": 1},
  {"category": "POLITYKA", "question": "Jaka słynna afera z 2002 roku dała początek pojęciu 'grupa trzymająca władzę'?", "answers": ["Afera hazardowa", "Afera Rywina", "Afera gruntowa", "Afera FOZZ"], "correct": 1},
  {"category": "TELEFONY", "question": "Gdzie trzeba było zajrzeć (lub wysłać stamtąd płatnego SMS-a), aby pobrać polifoniczny dzwonek na komórkę z początku dekady?", "answers": ["Do Google Play", "Na stronę Apple", "Do Telegazety lub gazety typu Bravo", "Do ustawień modemu"], "correct": 2},
  {"category": "SKANDALE", "question": "Gdzie w 2002 roku Edyta Górniak wykonała słynną, bardzo powolną interpretację hymnu Polski?", "answers": ["Na Igrzyskach Olimpijskich w Atenach", "Na Mistrzostwach Świata w piłce nożnej w Korei", "Na finale Ligi Mistrzów", "Na Eurowizji"], "correct": 1},
  {"category": "SERIALE PL", "question": "Jaki serial z Pawłem Małaszyńskim i Joanną Brodzik wyznaczał trendy na wielkomiejskie życie i randki w Warszawie?", "answers": ["Kasia i Tomek", "BrzydUla", "Magda M.", "Niania"], "correct": 2},
  {"category": "MUZYKA PL", "question": "Który polski duet DJ-ski i producencki rozniósł kluby hitem 'Explosion' w 2006 roku?", "answers": ["Kalwi & Remi", "MBrother", "C-Bool", "Max Farenthide"], "correct": 0},
  {"category": "TELEFONY", "question": "Jaka usługa operatorów pozwalała na to, by osoba dzwoniąca do Ciebie słyszała wybraną piosenkę zamiast nudnego sygnału oczekiwania?", "answers": ["Granie na Czekanie / Halo Granie", "Poczta Głosowa", "MMS z muzyką", "WAP Music"], "correct": 0},
  {"category": "INTERNET PL", "question": "Jaki polski serwis wideo (z charakterystycznym czerwonym playerem) królował u nas w czasach, gdy YouTube dopiero raczkował?", "answers": ["Smog.pl", "Wrzuta.pl", "CDA.pl", "Milanos.pl"], "correct": 1},
  {"category": "SKANDALE", "question": "O co pytała publiczność Mandaryna podczas swojego głośnego występu (często fałszując) na Sopot Festival 2005?", "answers": ["'Nie słyszę was!'", "'Znacie Ev'ry Night?!'", "'Polska, jazda!'", "'Dziękuję, dobranoc!'"], "correct": 1},
  {"category": "SERIALE PL", "question": "Jak nazywała się sąsiadka i najlepsza przyjaciółka Aliny Krawczyk z serialu 'Miodowe Lata'?", "answers": ["Danka Norek", "Zosia Krawczyk", "Krysia", "Basia Niedziela"], "correct": 0},
  {"category": "TV PL", "question": "Kto wygrał pierwszą, historyczną edycję programu 'Idol' w Polsce?", "answers": ["Krzysztof Zalewski", "Ewelina Flinta", "Alicja Janosz", "Szymon Wydra"], "correct": 2},
  {"category": "GRY", "question": "W jaką grę MMORPG zagrywano się masowo w polskich kafejkach, a wirtualne przedmioty z niej zalały raczkujące Allegro?", "answers": ["World of Warcraft", "Tibia", "Metin2", "Wszystkie z wymienionych"], "correct": 3},
  {"category": "TV PL", "question": "Z jakiego programu typu reality show pochodzi słynny tekst 'Chłopaki, nie pije bo jestem w ciąży!' (wypowiedziany rzekomo na wizji przez jedną z uczestniczek)?", "answers": ["Bar", "Dwa Światy", "Big Brother", "Agent"], "correct": 0},
  {"category": "POLITYKA", "question": "Kto wygrał wybory prezydenckie w Polsce w 2005 roku, pokonując w II turze Donalda Tuska?", "answers": ["Aleksander Kwaśniewski", "Andrzej Lepper", "Lech Kaczyński", "Bronisław Komorowski"], "correct": 2},
  {"category": "TELEFONY", "question": "Jaka sieć komórkowa weszła na polski rynek z hukiem w 2004 roku, reklamując się charakterystyczną czerwoną łapą?", "answers": ["Play", "Heyah", "Sami Swoi", "Mobile"], "correct": 1},
  {"category": "INTERNET PL", "question": "Komunikator Tlen.pl został stworzony przez i był ściśle zintegrowany z kontami pocztowymi na portalu...", "answers": ["Onet.pl", "WP.pl", "o2.pl", "Interia.pl"], "correct": 2},
  {"category": "TV PL", "question": "Kto prowadził kultowy program rozrywkowy w TVN i stworzył fikcyjną, satyryczną postać polityka Ędwarda Ąckiego?", "answers": ["Kuba Wojewódzki", "Marcin Prokop", "Szymon Majewski", "Piotr Bałtroczyk"], "correct": 2},
  {"category": "SKANDALE", "question": "O jakim 'dziadku' (w kontekście służby w Wehrmachcie) dyskutowano zawzięcie podczas polskiej kampanii prezydenckiej w 2005 roku?", "answers": ["Dziadku Lecha Wałęsy", "Dziadku Donalda Tuska", "Dziadku Lecha Kaczyńskiego", "Dziadku Włodzimierza Cimoszewicza"], "correct": 1},
  {"category": "MUZYKA PL", "question": "Piotr Kupicha i zespół Feel rozbili bank na festiwalu w Sopocie w 2007 roku utworem:", "answers": ["Pokonaj siebie", "Jak anioła głos", "Pokaż na co cię stać", "A gdy jest już ciemno"], "correct": 3},
  {"category": "SERIALE PL", "question": "Kto wspaniale grał rolę zwariowanej, pełnej tupetu i krzykliwych strojów opiekunki w serialu 'Niania'?", "answers": ["Anna Przybylska", "Agnieszka Dygant", "Katarzyna Figura", "Małgorzata Kożuchowska"], "correct": 1},
  {"category": "INTERNET PL", "question": "Jak nazywał się najpopularniejszy na początku XXI wieku polski portal służący do wrzucania swoich zdjęć do oceny?", "answers": ["Fotka.pl", "Sympatia.pl", "Badoo", "Grono.net"], "correct": 0},
  {"category": "TV PL", "question": "W którym teleturnieju z lat zerowych do wygrania i (najczęściej) wylosowania na koniec były pluszowe i narysowane 'Zonki'?", "answers": ["Koło Fortuny", "Idź na całość", "Grasz czy nie grasz", "Teleturniej"], "correct": 1},
  {"category": "POLITYKA", "question": "Jak publicyści i internauci potocznie nazywali rządzącą koalicję PiS, Samoobrony i LPR z lat 2006-2007?", "answers": ["Trójkąt Bermudzki", "Moherowa koalicja", "Koalicja Egzotyczna", "Solidarna Polska"], "correct": 1},
  {"category": "MUZYKA PL", "question": "Jakie imiona nosiły dwie dziewczyny z niezwykle popularnego pop-emo zespołu Blog 27?", "answers": ["Kasia i Gosia", "Tola i Alicja", "Ewa i Marina", "Doda i Maja"], "correct": 1},
  {"category": "TELEFONY", "question": "Jaka marka komórek uchodziła za absolutnie biznesową i 'premium' w drugiej połowie lat 2000, wyróżniając się sprzętową klawiaturą QWERTY?", "answers": ["BlackBerry", "Siemens", "Alcatel", "Sagem"], "correct": 0},
  {"category": "TV PL", "question": "Jaki program, w którym obcokrajowcy opowiadali o Polsce, prowadzony przez Monikę Richardson, gromadził przed ekranami TVP miliony widzów?", "answers": ["Europa da się lubić", "Sąsiedzi", "Świat to za mało", "Kocham Cię, Polsko!"], "correct": 0},
  {"category": "MUZYKA PL", "question": "Kto śpiewał w 2006 roku utwór 'Pozwól żyć', który stał się hymnem wielu złamanych nastoletnich serc?", "answers": ["Sylwia Grzeszczak", "Gosia Andrzejewicz", "Mezo", "Kasia Cerekwicka"], "correct": 1},
  {"category": "SERIALE PL", "question": "Jakiej marki jest fikcyjne piwo pite nieustannie przez Ferdynanda w serialu 'Świat według Kiepskich'?", "answers": ["Mocny Full", "Jasne Pełne", "Żubr", "Tatra"], "correct": 0},
  {"category": "FILM PL", "question": "Który polski komediodramat z 2002 roku zasłynął cytatami o odmienianiu słowa 'być' i narzekaniem na sypanie piasku po oknach?", "answers": ["Chłopaki nie płaczą", "Dzień Świra", "Poranek Kojota", "Kiler-ów 2-óch"], "correct": 1},
  {"category": "SPORT", "question": "Kto był 'cudotwórcą' na ławce trenerskiej reprezentacji Polski w piłce nożnej, wprowadzając ją na Mistrzostwa Europy 2008?", "answers": ["Jerzy Engel", "Paweł Janas", "Leo Beenhakker", "Franciszek Smuda"], "correct": 2},
  {"category": "INTERNET PL", "question": "Co trzeba było zdobyć od znajomego, by móc założyć konto w elitarnych pierwszych latach serwisu Grono.net?", "answers": ["Zaproszenie", "Skan dowodu osobistego", "Status studenta", "Konto bankowe"], "correct": 0},
  {"category": "TV PL", "question": "Jak miał na imię fajtłapowaty policjant 'z przypadku' grany przez Cezarego Pazurę w '13 posterunku'?", "answers": ["Cezary", "Bogusław", "Radosław", "Ksawery"], "correct": 0},
  {"category": "MUZYKA PL", "question": "Z kim Ewelina Flinta nagrała w 2005 roku ogromny hit 'Nie kłam, że kochasz mnie'?", "answers": ["Z nikim, śpiewała go sama", "Z Łukaszem Zagrobelnym", "Z Piotrem Kupichą", "Z Szymonem Wydrą"], "correct": 1},
  {"category": "TELEFONY", "question": "Jakie dwa magiczne słowa kryły się za wczesnym darmowym przesyłaniem dzwonków i tapet między telefonami (zanim nadeszło Wi-Fi Direct)?", "answers": ["Podczerwień i Bluetooth", "Kabel RJ-45 i Wi-Fi", "WAP i GPRS", "Modem i Dyskietka"], "correct": 0},
  {"category": "SKANDALE", "question": "O jakim skandalu seksualnym z posłem Łyżwińskim w tle informowała szeroko Gazeta Wyborcza pod koniec 2006 roku?", "answers": ["Seksaferze w Samoobronie", "Aferze taśmowej", "Aferze gruntowej", "Aferze podsłuchowej"], "correct": 0},
  {"category": "INTERNET PL", "question": "Do czego służyły w komunikatorze Gadu-Gadu słynne 'opisy' (statusy pod nazwą użytkownika)?", "answers": ["Do wrzucania zdjęć", "Do wpisywania przemyśleń, tekstów piosenek i cytatów", "Do grania w gry", "Do łączenia z naszą-klasą"], "correct": 1},
  {"category": "TV PL", "question": "Która stacja telewizyjna emitowała w popołudniowych paśmach kultowy talk-show 'Rozmowy w toku' z Ewą Drzyzgą?", "answers": ["Polsat", "TVP2", "TVN", "RTL7"], "correct": 2},
  {"category": "SPORT", "question": "W którym roku Robert Kubica zaliczył swój wyścigowy debiut w Formule 1?", "answers": ["2004", "2005", "2006", "2008"], "correct": 2},
  {"category": "MUZYKA PL", "question": "Jaka warszawska formacja muzyczna kierowana przez Muńka Staszczyka rzuciła stacje radiowe na kolana w 2001r. hitem 'Nie, nie, nie'?", "answers": ["Kult", "T.Love", "Myslovitz", "Strachy na Lachy"], "correct": 1},
  {"category": "SERIALE PL", "question": "Jakie imię nosił uwielbiany pies rasy Dogue de Bordeaux z serialu 'Rodzina zastępcza'?", "answers": ["Reksio", "Szarik", "Śliniak", "Baryła"], "correct": 2},
  {"category": "INTERNET PL", "question": "Co odpowiedział z okna mężczyzna wiszącemu na bloku śmiałkowi w kultowym filmiku 'Jestem Hardkorem' na YouTube?", "answers": ["'Będziesz to płacił'", "'Dawaj na dół, złaź!'", "'Będziesz leżał, człowieku!'", "'Wezwę policję'"], "correct": 2},
  {"category": "FILM PL", "question": "W jakiej hitowej komedii romantycznej z 2004 r. oparto fabułę na powieści Katarzyny Grocholi, a dom za miastem budowała Judyta?", "answers": ["Nigdy w życiu!", "Tylko mnie kochaj", "Dlaczego nie!", "Listy do M."], "correct": 0},
  {"category": "MODA", "question": "Co wpisywało się w modę szkolną wczesnych lat 2000., by wyglądać 'kreatywnie', przyczepiając to hurtowo na plecaki typu 'kostka'?", "answers": ["Naszywki zespołów muzycznych i agrafki", "Breloczki z postaciami Minecraft", "Breloki antystresowe", "Smycze z imionami od firm ubezpieczeniowych"], "correct": 0},
  {"category": "TV PL", "question": "Kto dwoił się i troił jako oryginalny prowadzący dynamiczny teleturniej 'Awantura o kasę' w telewizji Polsat?", "answers": ["Krzysztof Ibisz", "Hubert Urbański", "Maciej Kurzajewski", "Tomasz Kammel"], "correct": 0},
  {"category": "MUZYKA PL", "question": "Kto z dumą reprezentował Polskę na Eurowizji w 2003 z polsko-niemiecko-rosyjską piosenką 'Keine Grenzen', zgarniając 7. miejsce?", "answers": ["Edyta Górniak", "Ich Troje", "Blue Cafe", "Ivan i Delfin"], "correct": 1},
  {"category": "SERIALE PL", "question": "Kto jako 'Rysio' z 'Klanu' nakazywał legendarnie dzieciom 'umyjcie rączki' przed jedzeniem?", "answers": ["Tomasz Stockinger", "Piotr Cyrwus", "Andrzej Grabowski", "Cezary Żak"], "correct": 1},
  {"category": "TELEFONY", "question": "Z jakiego unikalnego jak na tamte czasy i prestiżowego kształtu słynął hit sprzedażowy z 2004 r. - telefon Motorola RAZR V3?", "answers": ["Kształt przypominał deskę do krojenia", "Miał slider z wysuwaną obudową w bok", "Miał ekran dotykowy z rysikiem", "Był klapką o niezwykle cienkim (brzytwiastym) profilu"], "correct": 3},
  {"category": "KOMPUTERY", "question": "Jaki program do bezlitosnego wypalania pirackich (i tych legalnych) płyt CD z logiem płonącego koloseum królował na pecetach?", "answers": ["Alcohol 120%", "Nero Burning ROM", "Deamon Tools", "CloneCD"], "correct": 1},
  {"category": "INTERNET PL", "question": "Jak nazywał się popularny, żółty serwis z dowcipami i śmiesznymi obrazkami przed erą Demotywatorów?", "answers": ["Joemonster.org", "Kwejk.pl", "Jbzd", "Wykop"], "correct": 0},
  {"category": "MUZYKA PL", "question": "Który polski zespół rockowy wydał w 2004 roku płytę 'Samotność po zmierzchu' z hitem 'Zanim pójdę'?", "answers": ["Coma", "Happysad", "Kult", "Strachy na Lachy"], "correct": 1},
  {"category": "TV PL", "question": "W jakim programie prowadzonym przez Zygmunta Chajzera uczestnicy zgadywali ceny produktów?", "answers": ["Dobra Cena", "Grasz czy nie grasz", "Idź na całość", "Cena marzeń"], "correct": 0},
  {"category": "FILM PL", "question": "Kto zagrał główną rolę (Kuby Brenner) w filmie 'Chłopaki nie płaczą'?", "answers": ["Cezary Pazura", "Maciej Stuhr", "Borys Szyc", "Tomasz Karolak"], "correct": 1},
  {"category": "POLITYKA", "question": "Który polityk zasłynął stwierdzeniem 'Yes, yes, yes!' po negocjacjach unijnych?", "answers": ["Lech Wałęsa", "Kazimierz Marcinkiewicz", "Donald Tusk", "Aleksander Kwaśniewski"], "correct": 1},
  {"category": "TELEFONY", "question": "Jaka usługa pozwalała wysyłać obrazki i dźwięki zanim spopularyzowały się MMS-y?", "answers": ["SMS Premium", "EMS (Enhanced Messaging Service)", "WAP", "Bluetooth"], "correct": 1},
  {"category": "SKANDALE", "question": "Jaka polska gwiazda wywołała oburzenie pozując do 'Playboya' z różańcem?", "answers": ["Doda", "Edyta Górniak", "Agnieszka Frykowska", "Kasia Kowalska"], "correct": 0},
  {"category": "GRY", "question": "W jakim kultowym polskim RPG z 2007 roku po raz pierwszy wcieliliśmy się w Geralta z Rivii?", "answers": ["Wiedźmin", "Gothic", "Two Worlds", "Cyberpunk 2077"], "correct": 0},
  {"category": "SERIALE PL", "question": "Jak miała na imię postać grana przez Joannę Brodzik, która szukała miłości w Warszawie pracując w agencji reklamowej?", "answers": ["Magda M.", "Kasia", "Niania Frania", "Ula Cieplak"], "correct": 0},
  {"category": "MUZYKA PL", "question": "Kto nagrał kontrowersyjny hit 'Oczy szeroko zamknięte' z teledyskiem w wannie?", "answers": ["Ewa Farna", "Virgin (Doda)", "Łzy (Ania Wyszkoni)", "O.N.A."], "correct": 2},
  {"category": "INTERNET PL", "question": "Jaki portal plotkarski z charakterystycznym, różowym logo zdominował polski internet w drugiej połowie lat 2000?", "answers": ["Pudelek.pl", "Kozaczek.pl", "Pomponik.pl", "Plotek.pl"], "correct": 0},
  {"category": "TV PL", "question": "Który z tych programów kulinarnych był emitowany na antenie TVN i prowadzony przez Pascala Brodnickiego?", "answers": ["Makłowicz w podróży", "Po prostu gotuj!", "Kuchenne rewolucje", "MasterChef"], "correct": 1},
  {"category": "POLITYKA", "question": "W którym roku tragicznie zginął prezydent Lech Kaczyński w katastrofie smoleńskiej, zamykając symboliczną dekadę lat 2000 w Polsce?", "answers": ["2008", "2009", "2010", "2011"], "correct": 2},
  {"category": "TELEFONY", "question": "Czym był 'Symbian' z perspektywy wczesnych smartfonów Nokii?", "answers": ["Marką słuchawek", "Systemem operacyjnym", "Gąbką do czyszczenia ekranu", "Protokołem internetowym"], "correct": 1},
  {"category": "SKANDALE", "question": "Kto rzucił legendarne 'Awanturujesz się!' do straży miejskiej w kultowym nagraniu?", "answers": ["Pan z 'Jestem Hardkorem'", "Krzysztof Kononowicz", "Pani Barbara", "Pan Wiesio"], "correct": 2},
  {"category": "MUZYKA PL", "question": "Który utwór Gosi Andrzejewicz stał się niekwestionowanym hitem list przebojów w 2006 roku?", "answers": ["Trochę ciepła", "Słowa", "Pozwól żyć", "Lustro"], "correct": 1},
  {"category": "SERIALE PL", "question": "Z jaką chorobą zmagał się proboszcz (Włodzimierz Matuszak) w serialu 'Plebania', co wywołało w internecie słynne wideo-przeróbki?", "answers": ["Z amnezją", "Z nadciśnieniem", "Z atakami kaszlu i duszności", "Z chorobą morską"], "correct": 2},
  {"category": "INTERNET PL", "question": "Jak miał na imię kandydat na prezydenta Białegostoku z 2006 r., który zasłynął hasłem 'Żeby nie było niczego'?", "answers": ["Krzysztof Kononowicz", "Lech Wałęsa", "Piotr Tymochowicz", "Bogusław Linda"], "correct": 0},
  {"category": "TV PL", "question": "Jak nazywał się reality show TVN z 2001 r., w którym uczestnicy pokonywali trasy i szukali kłamcy w swoim gronie?", "answers": ["Ryzykanci", "Wyprawa Robinson", "Agent", "Dwa Światy"], "correct": 2},
  {"category": "POLITYKA", "question": "Kto pełnił funkcję Premiera Polski w latach 2001-2004 (rząd SLD-UP)?", "answers": ["Leszek Miller", "Józef Oleksy", "Włodzimierz Cimoszewicz", "Jerzy Buzek"], "correct": 0},
  {"category": "MODA", "question": "Jaka 'biznesowa' torba często towarzyszyła dresom ortalionowym w stereotypowym wizerunku polskiego chuligana lat 2000?", "answers": ["Aktówka", "Saszetka tzw. 'nerka' lub 'kołczan prawilności'", "Plecak kostka", "Teczka skórzana"], "correct": 1},
  {"category": "FILM PL", "question": "W jakiej komedii z 2001 roku Michał Milowicz gra u boku Macieja Stuhra i wypowiada tekst o 'byle jakich małpach'?", "answers": ["Chłopaki nie płaczą", "Poranek Kojota", "Testosteron", "Lejdis"], "correct": 1},
  {"category": "MUZYKA PL", "question": "Jaki zespół z wokalistą Arturem Rojkiem w 2002 nagrał album 'Korova Milky Bar'?", "answers": ["O.N.A.", "IRA", "Myslovitz", "Republika"], "correct": 2},
  {"category": "GRY", "question": "Która platforma do dystrybucji cyfrowej (dziś gigant) była w latach 2000. hejtowana za wymóg instalacji przy grze Half-Life 2?", "answers": ["Origin", "GOG", "Uplay", "Steam"], "correct": 3},
  {"category": "INTERNET PL", "question": "Co symbolizowała 'dyskietka' w lewym górnym rogu wielu edytorów, chociaż nikt ich już fizycznie nie używał pod koniec dekady?", "answers": ["Ikonę zapisu (Save)", "Otwieranie pliku", "Drukowanie", "E-mail"], "correct": 0},
  {"category": "TV PL", "question": "W którym show tanecznym występował Michał Piróg i Agustin Egurrola jako sędziowie?", "answers": ["Taniec z Gwiazdami", "Got to Dance", "You Can Dance - Po prostu tańcz", "Dance Dance Dance"], "correct": 2},
  {"category": "SKANDALE", "question": "Z powodu jakiej wypowiedzi na scenie wokalistka Ich Troje, Justyna Majkowska, opuściła zespół?", "answers": ["Opuściła z innych powodów osobistych", "Pokłóciła się o stroje", "Zgubiła mikrofon na koncercie", "Pomyliła hymn na Eurowizji"], "correct": 0},
  {"category": "TELEFONY", "question": "Jaka darmowa, otwartoźródłowa przeglądarka internetowa wypuszczona w 2004 r. rzuciła wyzwanie Internet Explorerowi, wprowadzając karty?", "answers": ["Chrome", "Opera", "Firefox", "Safari"], "correct": 2},
  {"category": "SERIALE PL", "question": "Jaki zawód wykonywał serialowy tata (Piotr Fronczewski) w 'Rodzinie Zastępczej'?", "answers": ["Był lekarzem", "Był inżynierem architektem", "Był policjantem", "Był nauczycielem"], "correct": 1},
  {"category": "MUZYKA PL", "question": "Jaki utwór K.A.S.A. śpiewał z Marią Sadowską w teledysku przypominającym egzotyczną wyspę?", "answers": ["Macho", "Piękniejsza", "Każdy lubi boogie", "Smak 80-tych lat"], "correct": 0},
  {"category": "TV PL", "question": "W którym z programów rozrywkowych śpiewano na żywo teksty z 'producenckiego promptera' i oceniano wykonania piosenek karaoke?", "answers": ["Szansa na Sukces", "Jak oni śpiewają", "Droga do Gwiazd", "Twoja Twarz Brzmi Znajomo"], "correct": 1},
  {"category": "INTERNET PL", "question": "Jakie pliki najczęściej ściągało się przez Neostradę ze stron takich jak 'Pobieraczek', często nacinając się na ukryte opłaty?", "answers": ["Gry freeware", "Opracowania lektur szkolnych", "Filmy i piosenki", "Tapety HD"], "correct": 2},
  {"category": "POLITYKA", "question": "Jak nazywała się partia założona m.in. przez Janusza Palikota, która zadebiutowała silnym poparciem pod koniec lat 2000. / na początku 2010.?", "answers": ["Ruch Palikota", "Nowoczesna", "Wiosna", "Samoobrona"], "correct": 0},
  {"category": "SPORT", "question": "Który polski pływak zdobył złoto na IO w Atenach w 2004 roku na dystansie 200 m stylem motylkowym?", "answers": ["Paweł Korzeniowski", "Otylia Jędrzejczak", "Bartosz Kizierowski", "Mateusz Sawrymowicz"], "correct": 1},
  {"category": "MUZYKA PL", "question": "Jaki zespół wylansował piosenkę 'Otwórz oczy' z 2004 roku, będącą hymnem skejtów i fanów pop-punku w Polsce?", "answers": ["CF98", "Blink-182", "KSU", "Goya"], "correct": 0},
  {"category": "SERIALE PL", "question": "Z kim spotykała się Hanka Mostowiak w kartonach?", "answers": ["Z kierownicą", "Z niczym, po prostu w nie wjechała", "Z Markiem Mostowiakiem", "Z sarną na drodze"], "correct": 1},
  {"category": "FILM PL", "question": "Kto wcielił się w postać Wąskiego w filmie 'Kiler' oraz kontynuacji 'Kiler-ów 2-óch'?", "answers": ["Jerzy Stuhr", "Janusz Rewiński", "Krzysztof Kiersznowski", "Cezary Pazura"], "correct": 2},
  {"category": "INTERNET PL", "question": "Jak w GG oznaczało się linki wysyłane znajomym?", "answers": ["Znaczkiem @", "Podkreśleniem i niebieskim kolorem", "Nie można było wysyłać linków", "Musiały być w cudzysłowie"], "correct": 1},
  {"category": "TELEFONY", "question": "W co najczęściej graliśmy na wczesnych kolorowych komórkach (Java) przez Bluetooth ze znajomym na nudnych lekcjach?", "answers": ["Snake II", "Gravity Defied", "V-Rally 3D", "W statki (Naval Battle)"], "correct": 3},
  {"category": "MUZYKA PL", "question": "Która wokalistka solowa zdominowała polski pop-dance lat zerowych piosenkami takimi jak 'Cicho' czy 'EWA'?", "answers": ["Sylwia Grzeszczak", "Ewa Farna", "Honey (Honorata Skarbek)", "Marina Łuczenko"], "correct": 1},
  {"category": "TV PL", "question": "Jak nazywał się program typu talk-show w Polsacie, prowadzony przez Mariusza Szczygła?", "answers": ["Na każdy temat", "Rozmowy w toku", "Kuba Wojewódzki", "Wieczór z Wampirem"], "correct": 0},
  {"category": "SKANDALE", "question": "Kogo pobił Tomasz Lis według głośnego mema i fałszywych doniesień w internecie z końca dekady?", "answers": ["Kingę Rusin", "Księdza", "Borysa Szyca", "Wielkiego Ptaka z Ulicy Sezamkowej"], "correct": 0},
  {"category": "POLITYKA", "question": "Jaki urząd objął Donald Tusk w 2007 roku po wygranych wyborach parlamentarnych?", "answers": ["Prezydenta RP", "Premiera RP", "Marszałka Sejmu", "Prezesa NBP"], "correct": 1},
  {"category": "SERIALE PL", "question": "Jaki kultowy motyw przewodni zagrał i zaśpiewał zespół T.Love do serialu 'Kasia i Tomek'?", "answers": ["Warszawa", "Chłopaki nie płaczą", "Nie, nie, nie", "I love you"], "correct": 2},
  {"category": "GRY", "question": "Jaki przydomek nosił bohater serii 'Gothic', w którego wcielali się polscy gracze w latach 2000.?", "answers": ["Bezimienny", "Geralt", "Nerevarine", "Wybraniec"], "correct": 0},
  {"category": "INTERNET PL", "question": "Co krzyczał bohater wiralowego wideo z YouTube do kierowcy koparki?", "answers": ["Zostaw to!", "Panie, idź pan stąd!", "Urwał! Ale urwał!", "Ała, boli mnie to!"], "correct": 2},
  {"category": "SPORT", "question": "Który Polski bramkarz wykonał 'Dudek Dance' podczas finału Ligi Mistrzów w 2005 roku?", "answers": ["Wojciech Szczęsny", "Artur Boruc", "Łukasz Fabiański", "Jerzy Dudek"], "correct": 3},
  {"category": "TELEFONY", "question": "Ile znaków standardowo mieściło się w jednej niełączonej wiadomości SMS?", "answers": ["140", "160", "200", "255"], "correct": 1},
  {"category": "MUZYKA PL", "question": "Jaka raperka (Wdowa, Aśka?) nagrała głośny kawałek z Pezetem 'Seniorita'?", "answers": ["Nie było tam raperki, Pezet śpiewał z bratem", "Fisz", "Tede", "Ten Typ Mes"], "correct": 0},
  {"category": "TV PL", "question": "W którym teleturnieju do wygrania były legendarne 'Kufereczki'?", "answers": ["Milionerzy", "Grasz czy nie grasz", "Idź na całość", "Rosyjska ruletka"], "correct": 1},
  {"category": "INTERNET PL", "question": "Jak miał na imię kot z wiralowego wideo z syntezatorem mowy (Ivona), który miał wyjść na zewnątrz?", "answers": ["Mruczek", "Garfield", "Puszek", "Borys"], "correct": 2},
  {"category": "MUZYKA PL", "question": "Kto śpiewał kontrowersyjną, wulgarną piosenkę 'Gdzie jest biały węgorz? (Zejście)'?", "answers": ["Firma", "Cypis", "Popek", "Peja"], "correct": 1},
  {"category": "FILM PL", "question": "W jakiej produkcji zagrał Borys Szyc, grając kibola w bluzie dresowej u boku Mariana Dziędziela?", "answers": ["Symetria", "Wojna polsko-ruska", "Drogówka", "Pod Mocnym Aniołem"], "correct": 1},
  {"category": "SERIALE PL", "question": "Jak miał na imię niewidomy mafiozo grany przez Janusza Chabiora w serialu 'Ślepnąc od świateł' (choć to później, ale dotyczy dekad)? Wróćmy do 2000! Kto grał w 'Fali zbrodni'?", "answers": ["Jan Frycz", "Mirosław Baka", "Agnieszka Dygant", "Wszyscy wymienieni"], "correct": 3},
  {"category": "POLITYKA", "question": "Który polski prezydent zawetował najwięcej ustaw w historii III RP?", "answers": ["Aleksander Kwaśniewski", "Lech Kaczyński", "Lech Wałęsa", "Andrzej Duda"], "correct": 1},
  {"category": "TELEFONY", "question": "Czym był charakterystyczny joystick w popularnych telefonach Sony Ericsson z serii K?", "answers": ["Ozdobą", "Narzędziem, które ciągle się psuło i zacinało od kurzu", "Anteną", "Aparatem"], "correct": 1},
  {"category": "SKANDALE", "question": "Jaka sprawa sądowa związana z prawami autorskimi wstrząsnęła Polską, kiedy pozwanym był nastolatek ściągający film 'Dzień Świra'?", "answers": ["To plotka, nie było takiego wyroku", "Sprawa zamknięcia serwisu Napster w PL", "Wiele takich spraw miało miejsce przez pobieranie z torrentów i p2p", "Tylko ściąganie muzyki było karane"], "correct": 2},
  {"category": "GRY", "question": "Jak nazywała się gra wydana w 2001, gdzie budowano własne ZOO?", "answers": ["RollerCoaster Tycoon", "Zoo Tycoon", "The Sims: Zwierzaki", "Theme Park"], "correct": 1},
  {"category": "TV PL", "question": "Kto prowadził kultowy program MTV 'Pimp My Ride' (w polskiej wersji językowej lektorem był...)?", "answers": ["Xzibit", "Snoop Dogg", "Eminem", "Tede"], "correct": 0},
  {"category": "MUZYKA PL", "question": "Który zespół nagrał w 2000 roku płytę 'Kinematografia', która odmieniła polski hip-hop?", "answers": ["Kaliber 44", "Paktofonika", "Wzgórze Ya-Pa 3", "Molesta Ewenement"], "correct": 1},
  {"category": "INTERNET PL", "question": "Jak nazywał się najpopularniejszy polski serwis aukcyjny (i jest nim do dziś), który zadebiutował tuż przed rokiem 2000?", "answers": ["Świstak.pl", "Allegro.pl", "Ebay.pl", "OLX"], "correct": 1},
  {"category": "MODA", "question": "Jakie fryzury królowały u polskich nastolatków 'emo' ok. 2007-2009?", "answers": ["Trwała ondulacja", "Krótkie jeżyki z żelem", "Mocno wycieniowane, asymetryczne grzywki i tlenione pasemka", "Dredy"], "correct": 2},
  {"category": "SPORT", "question": "Kto zdobył pierwszy w historii polskiego wioślarstwa złoty medal olimpijski (Pekin 2008)?", "answers": ["Czwórka podwójna: Korol, Wasielewski, Kolbowicz, Jeliński", "Tomasz Kucharski i Robert Sycz", "Mateusz Kusznierewicz", "Magdalena Fularczyk"], "correct": 0},
  {"category": "SERIALE PL", "question": "W jakiej kamienicy w Warszawie toczyła się główna akcja serialu 'Miodowe Lata'?", "answers": ["Wolska 33", "Złota 44", "Wiejska 1", "Alternatywy 4"], "correct": 0},
  {"category": "TV PL", "question": "Jak nazywał się teleturniej w TVP2, w którym grało się w drużynach, układano hasła z liter i krzyczano 'Litera A!'?", "answers": ["Jaka to melodia", "Koło Fortuny", "Gili Gili", "Wielka Gra"], "correct": 1},
  {"category": "MUZYKA PL", "question": "Kto nagrał 'Sutki' - jeden z pierwszych szeroko komentowanych utworów rap na YouTube ok. 2007 r.?", "answers": ["Klocuch", "Grupa Operacyjna", "Bonus BGC", "Lech Roch Pawlak"], "correct": 1},
  {"category": "POLITYKA", "question": "Jaki był skrót Ligi Polskich Rodzin, partii wchodzącej w koalicję rządzącą z PiS?", "answers": ["LRP", "PRL", "LPR", "RP"], "correct": 2},
  {"category": "INTERNET PL", "question": "Jaką nazwę nosił darmowy host obrazków, na którym królowały memy zanim nastał imgur?", "answers": ["TinyPic", "ImageShack", "Fotosik.pl", "Wszystkie wymienione"], "correct": 3},
  {"category": "TELEFONY", "question": "Czym był popularny telefon Nokia N-Gage?", "answers": ["Pancernym telefonem dla drwali", "Połączeniem telefonu i przenośnej konsoli do gier (rozmowa 'na taco')", "Telefonem z klapką", "Pierwszym dotykowcem"], "correct": 1},
  {"category": "SKANDALE", "question": "Kto 'miał oddać za bilet' według bohatera wiralowego filmiku nagranego pod kasą w PKP?", "answers": ["'Dawaj moje 100 złotych!'", "'Będziesz Pan wisiał!'", "'Oddawaj za bilet z Pruszkowa!'", "'Panie, on mi za bilet wisi!'"], "correct": 0},
  {"category": "FILM PL", "question": "Kto wyreżyserował adaptację 'Wiedźmina' z 2001 r., która spotkała się z dużą krytyką za efekty specjalne (np. 'złotego smoka')?", "answers": ["Andrzej Wajda", "Marek Brodzki", "Jerzy Hoffman", "Patryk Vega"], "correct": 1},
  {"category": "SERIALE PL", "question": "Jak nazywała się żona Ferdynanda Kiepskiego?", "answers": ["Halina", "Helena", "Mariolka", "Bożena"], "correct": 0},
  {"category": "MUZYKA PL", "question": "Który polski raper zasłynął dissem 'W aucie' z Sokołem i Pono (2007)?", "answers": ["Jędker", "Fred", "Franek Kimono", "Piotr Fronczewski"], "correct": 3},
  {"category": "GRY", "question": "Jaka gra RTS od polskiego studia Reality Pump zyskała fanów dzięki świetnej kampanii (i magii na klawiaturze numerycznej)?", "answers": ["Polanie II", "Earth 2150", "Knights and Merchants", "Wszystkie z wymienionych to polskie RTSy, ale Reality Pump to Earth!"], "correct": 1},
  {"category": "TV PL", "question": "W którym z programów dzieci wylewały farbę na płótno w pracowni plastycznej ('Pan Kuleczka')?", "answers": ["Ciuchcia", "Pan Tik-Tak", "Domowe Przedszkole", "Teleferie"], "correct": 2},
  {"category": "INTERNET PL", "question": "Jak w GG oznaczało się nieobecność odchodząc od klawiatury?", "answers": ["AFK", "Z/W (Zaraz wracam)", "BRB", "DND"], "correct": 1},
  {"category": "SPORT", "question": "Kto skomentował historyczny rzut siatkarza ze słowami: 'Złotko moje, ty moje złotko, Wlazły...!'", "answers": ["Tomasz Zimoch", "Dariusz Szpakowski", "Włodzimierz Szaranowicz", "Mateusz Borek"], "correct": 0},
  {"category": "TELEFONY", "question": "Jaki innowacyjny gadżet był chowany z tyłu telefonu Sony Ericsson K750i pod specjalną, przesuwaną zasuwką?", "answers": ["Piórko rysika", "Obiektyw aparatu 2 Mpix", "Karta pamięci Memory Stick Duo", "Dodatkowa bateria"], "correct": 1},
  {"category": "MUZYKA PL", "question": "Co zaśpiewał zespół Akcent (Zenon Martyniuk), co wpisało się w kanon disco polo lat 00.?", "answers": ["Jesteś szalona", "Przez twe oczy zielone (to hit 2014, zmyłka!)", "Gwiazda", "Chłop z Mazur"], "correct": 2},
  {"category": "POLITYKA", "question": "Kto został Ministrem Edukacji w 2006 roku, wprowadzając m.in. postulat amnestii maturalnej i 'mundurki' w szkołach?", "answers": ["Anna Zalewska", "Roman Giertych", "Katarzyna Hall", "Krystyna Łybacka"], "correct": 1},
  {"category": "SKANDALE", "question": "Jaka dziennikarka straciła program po skandalu z wysmarowaniem twarzy 'kurzem' z biurka w programie TVN (afera 'Kupa Wojewódzki')?", "answers": ["Nie straciła, to była prowokacja", "Kazimiera Szczuka", "Agnieszka Szulim", "Agnieszka Chylińska"], "correct": 1},
  {"category": "SERIALE PL", "question": "Który serial przedstawiał perypetie oddziału policji na wrocławskim Ołbinie?", "answers": ["W11 - Wydział Śledczy", "Kryminalni", "Fala zbrodni", "Ojciec Mateusz"], "correct": 2},
  {"category": "FILM PL", "question": "Jakie miasto jest tłem dla filmu 'Vinci' w reż. Juliusza Machulskiego (2004)?", "answers": ["Warszawa", "Gdańsk", "Kraków", "Wrocław"], "correct": 2},
  {"category": "INTERNET PL", "question": "Jaki darmowy edytor tekstu stanowił trzon darmowego pakietu OpenOffice, ratując studentów przed kupnem Worda?", "answers": ["Calc", "Writer", "Impress", "Notepad++"], "correct": 1},
  {"category": "MUZYKA PL", "question": "Kto rapował 'Otwieram wino ze swoją dziewczyną' (2004)?", "answers": ["K.A.S.A.", "Mezo i Tabb", "Sidney Polak", "O.S.T.R."], "correct": 2},
  {"category": "TV PL", "question": "Jak nazywał się blok bajek i seriali anime emitowanych w niedziele rano na Polsacie (m.in. Pokemon, Dragon Ball)?", "answers": ["Fox Kids", "Jetix", "Polsat dla Dzieci (brak oficjalnej nazwy, po prostu pasmo)", "RTL 7"], "correct": 2},
  {"category": "TELEFONY", "question": "Ile kosztowało wysłanie jednego dzwonka lub tapety z telegazety / gazety (standardowa cena z gwiazdką)?", "answers": ["1,22 zł z VAT", "9,00 zł", "Około 10,98 zł z VAT (tzw. 9 zł + VAT)", "Darmowe"], "correct": 2},
  {"category": "GRY", "question": "Która gra MMO od polskich twórców (CD Projekt / GOG to wydawcy innych, ale Polacy zrobili to MMO...) z 2004 w klimacie sci-fi miała się zmierzyć z WoW?", "answers": ["Nie było takiej", "Tibia 2", "Margonem (Fantasy, nie sci-fi)", "Earth Eternal"], "correct": 0},
  {"category": "MUZYKA PL", "question": "Kto wydał w 2008 roku hitowy album 'Cicho', zgarniając m.in. Słowika Publiczności w Sopocie?", "answers": ["Doda", "Ewa Farna", "Gosia Andrzejewicz", "Kasia Kowalska"], "correct": 1},
  {"category": "INTERNET PL", "question": "Jaki syntezator mowy z charakterystycznym męskim głosem czytał większość polskich parodii i 'przeróbek' na wczesnym YT?", "answers": ["Ivona (głos Jacek)", "Google Translate", "Siri", "Cortana"], "correct": 0},
  {"category": "SPORT", "question": "Gdzie Polacy sensacyjnie zdobyli Wicemistrzostwo Świata w piłce ręcznej w 2007 r. (trenowani przez Bogdana Wentę)?", "answers": ["W Niemczech", "W Chorwacji", "We Francji", "W Polsce"], "correct": 0},
  {"category": "SERIALE PL", "question": "Jaka była ulubiona forma spędzania czasu (i picia) Jędruli i Posterunkowego w 'Rodzinie Zastępczej'?", "answers": ["Granie w szachy z koniakiem", "Picie nalewki w garażu/piwnicy u Fronczewskiego", "Wyjścia do pubu z bilardem", "Kawa w kuchni z ciastem Jadzi"], "correct": 1},
  {"category": "POLITYKA", "question": "Jaką obietnicę gospodarczą złożył Donald Tusk w swoim słynnym exposé (dot. emigrantów), mówiąc o powrotach z Wysp?", "answers": ["Że w Polsce będzie 'Druga Japonia'", "Że powstaną 'Szklane domy'", "Że w Polsce będzie 'Zielona Wyspa' i 'Powrót z emigracji'", "Wszystko powyższe"], "correct": 2},
  {"category": "FILM PL", "question": "W jakiej produkcji z 2003 roku bohaterowie, Maciej i Bartek, uciekali skradzionym Mercedesem na południe?", "answers": ["Czas surferów", "Ciało", "Zróbmy sobie wnuka", "Złoty Środek"], "correct": 1},
  {"category": "MUZYKA PL", "question": "Która uczestniczka 'Idola' zasłynęła charakterystycznym krzykiem i wykonaniem 'Jaskółki uwięzionej' (a potem płytą z hitem 'Moje pijaństwo')?", "answers": ["Brodka", "Ala Janosz", "Ewelina Flinta", "Agnieszka Chylińska (nie była w Idolu)"], "correct": 2},
  {"category": "TV PL", "question": "Kto w 2000 roku poprowadził w TVN pierwszy sezon teleturnieju 'Milionerzy', wprowadzając kultowe 'Czy to jest twoja ostateczna odpowiedź?'", "answers": ["Krzysztof Ibisz", "Hubert Urbański", "Zygmunt Chajzer", "Piotr Gąsowski"], "correct": 1},
  {"category": "TELEFONY", "question": "Jaka usługa operatorska z wczesnych lat 00. pozwalała na połączenie się z bardzo okrojoną wersją internetu tekstowego na telefonach?", "answers": ["Edge", "WAP", "LTE", "GPRS (WAP korzystał z niego, ale to WAP był usługą przeglądania)"], "correct": 1},
  {"category": "INTERNET PL", "question": "Kto nagrał słynny filmik 'Będę grał w grę', odpowiadając na pytanie o plany na Sylwestra?", "answers": ["Pewien zrezygnowany pan w wywiadzie ulicznym", "Klocuch", "Zwykły gracz z kafejki internetowej zapytany przez dziennikarkę, grający w Tomb Raidera", "Tomek z Torunia"], "correct": 2},
  {"category": "SPORT", "question": "Kto jako pierwszy polski kierowca wygrał w 2008 roku wyścig Formuły 1 (Grand Prix Kanady)?", "answers": ["Krzysztof Hołowczyc", "Leszek Kuzaj", "Robert Kubica", "Michał Kościuszko"], "correct": 2},
  {"category": "MUZYKA PL", "question": "Z jakiego utworu Kasy (Krzysztofa Kasowskiego) pochodzą słowa 'Maczo, to chłop co w mordę lać nie musi'?", "answers": ["Piękniejsza", "Macho", "Wino", "Dżaga"], "correct": 1},
  {"category": "INTERNET PL", "question": "Jaka legendarna emotikona na GG przedstawiała uderzanie głową w mur?", "answers": ["<mur>", "<bang>", "<ściana>", "<wall>"], "correct": 3},
  {"category": "TV PL", "question": "Kto śpiewał czołówkę do programu 'Kawa czy Herbata' w latach 2000.?", "answers": ["Andrzej Piaseczny", "Ryszard Rynkowski", "Zbigniew Wodecki", "Krzysztof Krawczyk"], "correct": 0},
  {"category": "MUZYKA PL", "question": "Która piosenka była hitem debiutanckiego albumu Moniki Brodki w 2004 roku?", "answers": ["Dziewczyna mojego chłopaka", "Ten", "Miałeś być", "Znam Cię na pamięć"], "correct": 1},
  {"category": "FILM PL", "question": "W którym roku odbyła się premiera filmu 'Katyń' w reżyserii Andrzeja Wajdy?", "answers": ["2005", "2006", "2007", "2008"], "correct": 2},
  {"category": "GRY", "question": "Jaka kultowa polska gra akcji z elementami FPS z 2004 roku pozwalała walczyć z demonami i wywołała aferę religijną na Zachodzie?", "answers": ["Call of Juarez", "Painkiller", "Dead Island", "Sniper: Ghost Warrior"], "correct": 1},
  {"category": "TELEFONY", "question": "Jaka usługa wprowadzona przez operatorów w latach 2000. pozwalała na nielimitowane rozmowy tylko z jedną, wybraną osobą?", "answers": ["Bezpłatny Weekend", "Darmowy Numer / Wybrany Numer", "Pakiet 100 Minut", "Złota Karta"], "correct": 1},
  {"category": "SERIALE PL", "question": "Kto wcielał się w postać Karola Krawczyka, nerwowego motorniczego tramwaju w 'Miodowych Latach'?", "answers": ["Artur Barciś", "Cezary Żak", "Piotr Fronczewski", "Tomasz Karolak"], "correct": 1},
  {"category": "POLITYKA", "question": "Jak miała na imię słynna posłanka Samoobrony, która twierdziła, że 'kurwiki z oczu jej nie zniknęły'?", "answers": ["Wanda Nowicka", "Renata Beger", "Danuta Hojarska", "Krystyna Łybacka"], "correct": 1},
  {"category": "SKANDALE", "question": "Jaki program w TVN wywołał skandal po odcinku, w którym uczestniczka (w obecności wykrywacza kłamstw) przyznała się do zdrady narzeczonego?", "answers": ["Wybacz mi", "Nic straconego", "Moment Prawdy", "Rozmowy w Toku"], "correct": 2},
  {"category": "SPORT", "question": "Gdzie reprezentacja Polski w siatkówce mężczyzn zdobyła srebrny medal Mistrzostw Świata w 2006 roku?", "answers": ["W Polsce", "We Włoszech", "W Japonii", "W Brazylii"], "correct": 2},
  {"category": "MODA", "question": "Jakie spodnie dresowe z białymi lampasami były absolutnym must-have każdego 'prawilnego' blokersa z lat zerowych?", "answers": ["Puma", "Nike", "Adidas", "Reebok"], "correct": 2},
  {"category": "INTERNET", "question": "Jaki komunikator (z ikonką kwiatuszka) był głównym globalnym konkurentem MSN przed erą Facebooka, choć w PL przegrywał z GG?", "answers": ["ICQ", "Yahoo Messenger", "Skype", "AOL"], "correct": 0},
  {"category": "MUZYKA", "question": "Jaki zespół z Las Vegas nagrał w 2004 roku alternatywny hymn parkietów 'Mr. Brightside'?", "answers": ["The Strokes", "The Killers", "Arctic Monkeys", "Franz Ferdinand"], "correct": 1},
  {"category": "TV PL", "question": "W którym z programów Edyta Górniak i Doda zasiadały razem (i bardzo głośno się kłóciły) w jury?", "answers": ["Jak oni śpiewają", "The Voice of Poland", "Bitwa na Głosy", "Gwiazdy tańczą na lodzie"], "correct": 0},
  {"category": "KOMPUTERY", "question": "Jaki program antywirusowy najczęściej 'krzyczał' o aktualizacji bazy wirusów głosem lektora: 'Baza wirusów programu... została zaktualizowana'?", "answers": ["Norton", "Kaspersky", "Avast", "Avira"], "correct": 2},
  {"category": "SERIALE PL", "question": "Jak miał na imię wujek Stefan, wiecznie sprowadzający kłopoty brat Karola Krawczyka w późniejszych 'Miodowych Latach' (a dokładniej: 'Całkiem nowych latach')?", "answers": ["Nie było takiego wujka", "Wujek Leon", "Wujek Roman", "Wujek Zenek"], "correct": 0},
  {"category": "MUZYKA PL", "question": "Jaki polski DJ stworzył popularny wtedy na komórkach (i remiksowany w nieskończoność) utwór 'Insomnia'? (Zmyłka: to hit Faithless, kto w PL tworzył hity techno?) C-Bool stworzył:", "answers": ["Would You Feel", "Explosion", "Do You Know", "Call Me"], "correct": 0},
  {"category": "GRY", "question": "Jak nazywała się pierwsza konsola Microsoftu, która zadebiutowała w Europie na początku lat 2000., konkurując z PS2?", "answers": ["Xbox 360", "Xbox", "Xbox One", "Xbox Series"], "correct": 1},
  {"category": "TELEFONY", "question": "Czym były popularne na Sony Ericssonach pliki .thm?", "answers": ["Tapetami", "Dzwonkami", "Motywami (Themes) zmieniającymi całe menu", "Grami"], "correct": 2},
  {"category": "FILM PL", "question": "Kto zagrał Liptona w polskiej komedii o maturzystach 'Czas surferów' z 2005 roku?", "answers": ["Bogusław Linda", "Maciej Stuhr", "Michał Koterski", "Borys Szyc"], "correct": 0},
  {"category": "INTERNET PL", "question": "W którym roku oficjalnie uruchomiono serwis Nasza-Klasa.pl?", "answers": ["2004", "2005", "2006", "2007"], "correct": 2},
  {"category": "POLITYKA", "question": "Jak nazywał się wicepremier w rządzie Kaczyńskiego, lider LPR, który wprowadził mundurki do szkół?", "answers": ["Andrzej Lepper", "Roman Giertych", "Przemysław Gosiewski", "Marek Kuchciński"], "correct": 1},
  {"category": "SKANDALE", "question": "Kto wydał głośną w latach 2000. książkę 'Pamiętnik z okresu dojrzewania', pełną skandalizującego wtedy języka (choć to książka z '96, wywiady robiła w 00)?", "answers": ["Dorota Masłowska (to Wojna Polsko-Ruska)", "Blanka Lipińska", "Katarzyna Grochola", "Kinga Dunin"], "correct": 0},
  {"category": "TV", "question": "Jaki kultowy serial MTV opowiadał o grupie znajomych jeżdżących na deskorolkach i robiących sobie drastyczne, kaskaderskie żarty?", "answers": ["Viva La Bam", "Dirty Sanchez", "Jackass", "Wildboyz"], "correct": 2},
  {"category": "SPORT", "question": "W jakim klubie Artur Boruc spędził lata 2005-2010, zyskując status legendy i przydomek 'Holy Goalie'?", "answers": ["Fiorentina", "Legia Warszawa", "Celtic Glasgow", "Southampton"], "correct": 2},
  {"category": "MUZYKA PL", "question": "Z jakiego miasta wywodzi się hip-hopowy zespół Paktofonika?", "answers": ["Z Warszawy", "Z Poznania", "Z Katowic", "Z Kielc"], "correct": 2},
  {"category": "SERIALE PL", "question": "Kto wcielił się w postać podkomisarza 'Despero' w kultowym serialu policyjnym 'Pitbull' z 2005 roku?", "answers": ["Andrzej Grabowski", "Marcin Dorociński", "Janusz Gajos", "Paweł Królikowski"], "correct": 1},
  {"category": "INTERNET PL", "question": "Co pisało się w oknie konsoli Windowsa (cmd), aby sprawdzić, czy działa nam internet, często pingując portal Wirtualna Polska?", "answers": ["ping wp.pl", "ipconfig", "tracert wp.pl", "netstat"], "correct": 0},
  {"category": "GRY", "question": "Jak nazywał się dodatek do The Sims 2 z 2006 roku, który dodawał zwierzaki domowe?", "answers": ["Zwierzaki (Pets)", "Na Studiach", "Nocne Życie", "Cztery Pory Roku"], "correct": 0},
  {"category": "TELEFONY", "question": "Jaka popularna w Polsce firma produkowała telefony z serii 'Sagem'?", "answers": ["Niemiecka", "Szwedzka", "Francuska", "Koreańska"], "correct": 2},
  {"category": "TV PL", "question": "Jak miał na imię pierwszy polski prowadzący show 'Wipeout – Wymiatacze', komentujący z charakterystycznym luzem?", "answers": ["Tomasz Kammel", "Maciej Kurzajewski", "Krzysztof 'Jankes' Jankowski", "Marcin Prokop"], "correct": 2},
  {"category": "FILM PL", "question": "Który film wyreżyserował Patryk Vega w 2005 roku, rzucając cień na polską policję i tworząc podwaliny pod popularność swoich produkcji?", "answers": ["Kobiety Mafii", "Botoks", "Pitbull", "Służby specjalne"], "correct": 2},
  {"category": "MUZYKA PL", "question": "Jak brzmiał tytuł debiutanckiej płyty Dody i zespołu Virgin z 2002 roku?", "answers": ["Bimbo", "Ficca", "Virgin", "Choni"], "correct": 2},
  {"category": "SKANDALE", "question": "Kto wywołał skandal w 2007 r., drąc Biblię na scenie podczas koncertu i krzycząc, że Kościół katolicki to zbrodnicza sekta?", "answers": ["Nergal (Behemoth)", "Roman Kostrzewski (KAT)", "Doda", "Maleńczuk"], "correct": 0},
  {"category": "SPORT", "question": "Na których igrzyskach olimpijskich Otylia Jędrzejczak zdobyła trzy medale (złoto i dwa srebra)?", "answers": ["Sydney 2000", "Ateny 2004", "Pekin 2008", "Londyn 2012"], "correct": 1},
  {"category": "POLITYKA", "question": "Z jakiej stacji radiowej wywodziła się partia polityczna o nazwie 'Racja Polskiej Lewicy', mocno antyklerykalna w latach 2000?", "answers": ["Radio Zet", "Radio Maryja (nie, wręcz przeciwnie!)", "Antyradio", "Tygodnik NIE / Fakty i Mity (założycielem był R. Kotliński)"], "correct": 3},
  {"category": "KOMPUTERY", "question": "Jakie kultowe odgłosy wydawał komunikator Gadu-Gadu przy przyjściu nowej wiadomości?", "answers": ["Dzwonek rowerowy", "Głośne pikanie dwutonowe i chrobotanie głośników", "Charakterystyczny gwizdek", "Pukanie do drzwi i otwieranie zawiasów"], "correct": 1},
  {"category": "SERIALE PL", "question": "Jak miała na imię postać grana przez Krystynę Jandę w serialu medycznym 'Klub Szalonych Dziewic'? (Zmyłka: Janda nie grała w tym). Wróćmy do klasyków: kto prowadził pub w serialu 'Złotopolscy'?", "answers": ["Wiesław Gabriel", "Jan Złotopolski", "Dionizy Złotopolski", "Zenek z 'Kiepskich'"], "correct": 0},
  {"category": "INTERNET PL", "question": "Co oznaczało popularne przed laty 'ROTFL' wpisywane na forach?", "answers": ["Running On The Floor Laughing", "Rolling On The Floor Laughing", "Read Only Text For Losers", "Return Of The Funny Lion"], "correct": 1},
  {"category": "MUZYKA PL", "question": "Z jakiego polskiego filmu pochodzi piosenka 'Duchy tych co mieszkali tu' (WWO)?", "answers": ["Pitbull", "Symetria", "Czas Surferów", "Francuski Numer"], "correct": 1},
  {"category": "GRY", "question": "Jaka strona internetowa była mekką polskich darmowych gier we flashu (np. z Yeti grającym w pingwina)?", "answers": ["Cda.pl", "Gry.pl", "Wyspagier.pl", "Wszystkie wymienione"], "correct": 3},
  {"category": "TELEFONY", "question": "Ile kosztowało utrzymanie numeru 'na kartę' – co trzeba było robić co miesiąc, by nie zablokowali połączeń wychodzących?", "answers": ["Płacić stały abonament", "Wysyłać darmowy SMS", "Kupować tzw. 'zdrapkę' (doładowanie)", "Logować się na stronę operatora"], "correct": 2},
  {"category": "FILM PL", "question": "Kto zagrał głównego bohatera, Silnego, w ekranizacji 'Wojny polsko-ruskiej pod flagą biało-czerwoną' (2009)?", "answers": ["Eryk Lubos", "Borys Szyc", "Tomasz Karolak", "Maciej Stuhr"], "correct": 1},
  {"category": "TV PL", "question": "Jaki program kulinarny opierał się na tym, że dwóch kucharzy o imieniach Karol i Maciej gotowało potrawy w terenie?", "answers": ["Kuchenne ewolucje", "Pascal po prostu gotuj", "Gotuj z Kuroniem", "Nie z tej ziemi (chodzi o 'Smaki świata', poprawnie to 'Gotuj z Kuroniem' - tu zmyłka, Maciej i Karol to 'Okrasa łamie przepisy' - w sumie żadne z wymienionych. Odp brzmi: nikt tak nie robił pod tym tytułem, ale Okrasa tak gotował w 2003!)", "Zostawmy to, jaki tytuł: PRAWIDŁOWE: Kto prowadził 'Rower Błażeja'?", "Paulina Chylewska"], "correct": 3},
  {"category": "MODA", "question": "Jaki element biżuterii był niezwykle modny u mężczyzn (i wielu chłopców w szkołach) ok. 2002 roku?", "answers": ["Szerokie łańcuchy 'pancerki'", "Koraliki z muszelek na szyi (puka shells)", "Kolczyk w obu uszach", "Skórzane obroże"], "correct": 1},
  {"category": "SPORT", "question": "W jakim klubie grał Maciej Żurawski ('Magic') po opuszczeniu Wisły Kraków w 2005 roku?", "answers": ["Celtic Glasgow", "Southampton", "Borussia Dortmund", "Panathinaikos"], "correct": 0},
  {"category": "SKANDALE", "question": "Jakie zwierzę 'obraził' (a raczej żartował z niego) Kuba Wojewódzki, wywołując protesty organizacji praw zwierząt, gdy wkładał je w programie do czegoś na kształt blendera?", "answers": ["Złotą rybkę", "Chomika", "Świnkę Morską", "Psa pluto"], "correct": 1},
  {"category": "INTERNET PL", "question": "Jaki portal społecznościowy przed Facebookiem posiadał tzw. 'Kluby', do których można było dołączać (często z nazwami typu 'Nie lubię poniedziałków')?", "answers": ["Epuls", "Grono.net", "Nasza Klasa", "Photoblog.pl"], "correct": 1},
  {"category": "MUZYKA PL", "question": "Kto śpiewał w 2008 roku hit 'Jak anioła głos'?", "answers": ["Szymon Wydra", "Jacek Stachursky", "Piotr Kupicha (Feel)", "Andrzej Piaseczny"], "correct": 2},
  {"category": "POLITYKA", "question": "Kto był marszałkiem Sejmu z ramienia PiS, który w 2007 r. nosił charakterystyczne, długie, białe włosy?", "answers": ["Marek Jurek", "Ludwik Dorn", "Maciej Płażyński", "Bronisław Komorowski"], "correct": 1},
  {"category": "SERIALE PL", "question": "Gdzie rozgrywała się akcja popularnej opery mydlanej 'Na Wspólnej' (przynajmniej z nazwy serialu)?", "answers": ["W kamienicy w Krakowie", "Na nowym osiedlu w Poznaniu", "W apartamentowcu w Gdyni", "W bloku przy ul. Na Wspólnej w Warszawie"], "correct": 3},
  {"category": "MUZYKA PL", "question": "Który polski zespół z dwiema wokalistkami wydał świetnie przyjętą płytę 'Siła sióstr' (2003)?", "answers": ["Sistars", "Virgin", "Tatu", "Blog 27"], "correct": 0},
  {"category": "INTERNET", "question": "Jak nazywała się najpopularniejsza wczesna gra we flashu, w której Yeti uderzało kijem i odbijało lecącego pingwina?", "answers": ["Penguin Strike", "YetiSports", "Snow Bash", "Pingu Flight"], "correct": 1},
  {"category": "TELEFONY", "question": "Który model Sony Ericssona, wydany w 2004 roku, zrewolucjonizował słuchanie MP3 w telefonie dzięki dołączanym, dokanałowym słuchawkom Walkman?", "answers": ["W800i", "K700i", "T68i", "K800i"], "correct": 0},
  {"category": "POLITYKA", "question": "Do kogo skierowane było słynne hasło 'Spieprzaj dziadu!', wypowiedziane w 2002 roku?", "answers": ["Do protestującego rolnika", "Do dziennikarza TVN", "Do nachalnego przechodnia na warszawskiej Pradze", "Do posła w Sejmie"], "correct": 2},
  {"category": "SKANDALE", "question": "O czym rzekomo pisał 'Super Express' na pierwszej stronie pod zdjęciem mężczyzny trzymającego martwego ptaka?", "answers": ["'Nie śpię, bo trzymam kredens'", "'To on zjadł łabędzia w parku'", "'Uratowałem go z pożaru'", "'Gołębie kradną mi chleb'"], "correct": 0},
  {"category": "SPORT", "question": "Kto został wybrany 'Najlepszym piłkarzem MŚ 2002' w kadrze Polski (choć Polska szybko odpadła)?", "answers": ["Emmanuel Olisadebe", "Piotr Świerczewski", "Maciej Żurawski", "Edi Andradina"], "correct": 0},
  {"category": "TV PL", "question": "Jak miał na imię detektyw Rutkowski w programie 'Detektyw' na antenie TVN?", "answers": ["Jan", "Krzysztof", "Andrzej", "Piotr"], "correct": 1},
  {"category": "MUZYKA PL", "question": "Kto wraz z Liberem i Doniem założył kultowy hip-hopowy zespół Ascetoholix?", "answers": ["Mezo", "Peja", "Owal/Emcedwa", "Kris"], "correct": 3},
  {"category": "GRY", "question": "Jaką nazwę nosiła pierwsza odsłona wyścigów Need For Speed oparta o kulturę nielegalnego tuningu aut (2003)?", "answers": ["Carbon", "Undercover", "Underground", "Most Wanted"], "correct": 2},
  {"category": "INTERNET PL", "question": "Czym były 'Eurogąbki' w serwisie Nasza-Klasa?", "answers": ["Wirtualną walutą do kupowania wirtualnych prezentów i usług", "Gąbkami do czyszczenia ekranu ze sklepu serwisu", "Bonusowymi emotkami", "Odznakami za bycie online"], "correct": 0},
  {"category": "MODA", "question": "Jaki owad był częstym motywem na biżuterii, koszulkach i spinkach do włosów na początku lat 2000.?", "answers": ["Biedronka", "Motyl", "Ważka", "Pszczoła"], "correct": 1},
  {"category": "TELEFONY", "question": "Co trzeba było pobrać za pomocą WAP, by komórka odgrywała pełny hit z radia, a nie pikanie?", "answers": ["MP3 TrueTone", "Dzwonek polifoniczny lub Truetone/MP3", "MIDI Master", "Kod źródłowy"], "correct": 1},
  {"category": "TV", "question": "Jak nazywał się popularny kanał muzyczny z niemieckim pochodzeniem, wielki rywal MTV Polska w dekadzie zerowej?", "answers": ["Viva Polska", "4fun.tv", "Trace TV", "Polonia 1"], "correct": 0},
  {"category": "FILM PL", "question": "Jakie ptaki często powracały jako temat humorystyczny w komediach np. 'Chłopaki nie płaczą' czy w dialogach z 'Poranka Kojota'?", "answers": ["Bociany", "Sokoły", "Papugi", "Kormorany"], "correct": 3},
  {"category": "SKANDALE", "question": "Co stało się z popularnym swego czasu w internecie psem Leszkiem?", "answers": ["Uciekł z domu", "Zrobił prawo jazdy na memach", "Został skradziony", "Chciał 'dostać po ryju' (w satyrycznym dubbingu)"], "correct": 3},
  {"category": "SPORT", "question": "Kto znokautował w 2005 r. 'Białego Nadzieję' Andrzeja Gołotę w zaledwie 53 sekundy?", "answers": ["Lennox Lewis", "Lamon Brewster", "Mike Tyson", "John Ruiz"], "correct": 1},
  {"category": "SERIALE PL", "question": "Kto grał rolę kultowego Marka Dobrzańskiego, szefa domu mody Febo & Dobrzański w serialu 'BrzydUla'?", "answers": ["Mikołaj Roznerski", "Paweł Małaszyński", "Filip Bobek", "Maciej Zakościelny"], "correct": 2},
  {"category": "MUZYKA", "question": "Kto zszokował MTV VMA w 2003 roku, całując się na scenie z Madonną?", "answers": ["Britney Spears i Christina Aguilera", "Pink i Gwen Stefani", "Avril Lavigne", "Kelly Osbourne"], "correct": 0},
  {"category": "INTERNET", "question": "Jaka przeglądarkowa gra kosmiczna dzieliła graczy na sojusze i kazała im wstawać w środku nocy (tzw. fleet save)?", "answers": ["Plemiona", "Ogame", "BiteFight", "Travian"], "correct": 1},
  {"category": "POLITYKA", "question": "Kto w 2001 roku stworzył partię polityczną 'Samoobrona Rzeczpospolitej Polskiej' znanej m.in. z blokad dróg?", "answers": ["Andrzej Lepper", "Krzysztof Kononowicz", "Stanisław Tymiński", "Gabriel Janowski"], "correct": 0},
  {"category": "TV PL", "question": "Jaki tytuł nosił popularny talk-show prowadzony przez Wojciecha Jagielskiego w latach 1998-2003, często goszczący wampiry... a nie, to tytuł!", "answers": ["Wieczór z Wampirem", "Miasto Prywatne", "Rozmowy w Toku", "WC Kwadrans"], "correct": 0},
  {"category": "TELEFONY", "question": "Czym charakteryzował się telefon Sony Ericsson W900i, flagowiec z serii Walkman (2005)?", "answers": ["Miał wbudowany projektor", "Miał ekran dotykowy i rysik", "Był tzw. 'swivelem' (klapka otwierana przez obrót)", "Miał antenę do łapania sygnału TV"], "correct": 2},
  {"category": "MUZYKA PL", "question": "Która uczestniczka drugiej edycji Idola wydała wielki hit 'Zapamiętaj' w 2005 r. pod szyldem własnego imienia?", "answers": ["Krzysztof Zalewski", "Monika Brodka", "Ania Dąbrowska", "Ewelina Flinta"], "correct": 2},
  {"category": "SKANDALE", "question": "Z czego zasłynął Piotr Rubik w 2007 roku w relacjach z mediami?", "answers": ["Pokłócił się o prawa autorskie do 'Klaskania' (Tu non l'hai capisci)", "Oddzielił się od solistów i założył nową orkiestrę, kłócąc się o prawa do twórczości z Igorem Jaszczukiem/Katarzyną Kanclerz", "Rzucił nutami w dziennikarza", "Odmówił dyrygowania na żywo"], "correct": 1},
  {"category": "GRY", "question": "W co grało się pod Windowsem XP, gdy internet na 'Neostradzie' znowu przestał działać, oprócz Pasjansa i Sapera?", "answers": ["Space Cadet 3D Pinball", "Chess Titans", "Hover!", "Purble Place"], "correct": 0},
  {"category": "INTERNET PL", "question": "Co to był 'Sinfobot' lub 'Infobot' na platformie Gadu-Gadu?", "answers": ["Wirus kradnący hasła", "Oficjalne wsparcie GG", "Boty, do których pisało się komendy by sprawdzić pogodę, rozkład jazdy czy kurs walut", "Pierwszy polski ChatGPT"], "correct": 2},
  {"category": "SERIALE PL", "question": "Jak nazywała się fikcyjna podwarszawska miejscowość, w której toczyła się akcja serialu 'Złotopolscy'?", "answers": ["Złotopole", "Grabina", "Królowy Most", "Wilkowyje"], "correct": 0},
  {"category": "MODA", "question": "Jaką część bielizny kobiety często ostentacyjnie wystawiały ponad linię spodni biodrówek ok. 2004 roku?", "answers": ["Pończochy", "Rajstopy z lycry", "Szerokie gumki od bokserek (styl na Aaliyah)", "Paski od stringów (często tzw. 'whale tail')"], "correct": 3},
  {"category": "SPORT", "question": "Jakiego wyczynu dokonał Tomasz Sikora w 2004 roku jako pierwszy Polak w historii?", "answers": ["Został Mistrzem Świata w Biathlonie", "Zdobył żółtą koszulkę lidera Tour de Pologne", "Przeskoczył Adama Małysza", "Przepłynął wpław kanał La Manche"], "correct": 0},
  {"category": "MUZYKA", "question": "Która wokalistka nagrała kultowy r'n'b hit 'Family Affair' (2001)?", "answers": ["TLC", "Beyonce", "Mary J. Blige", "Alicia Keys"], "correct": 2},
  {"category": "POLITYKA", "question": "Kto zasłynął stwierdzeniem: 'Prawdziwego mężczyznę poznaje się nie po tym jak zaczyna, ale jak kończy'?", "answers": ["Lech Wałęsa", "Leszek Miller", "Aleksander Kwaśniewski", "Andrzej Lepper"], "correct": 1},
  {"category": "TV PL", "question": "W którym reality show uczestnicy byli zamknięci na dwa miesiące w różowym 'domku' pełnym kamer (telewizja Polsat)?", "answers": ["Bar", "Dwa Światy", "Big Brother", "Łysi i Blondynki (był taki eksperyment na MTV, ale tu Polsat) – Prawidłowa to 'Dwa Światy' (lub 'Amazonki' / 'Gladiatorzy'!) Pytanie dotyczy Polsatu. W którym zamknęli w różowym domku? W 'Amazonkach' i 'Gladiatorach'!"], "correct": 3},
  {"category": "TELEFONY", "question": "Jakie złącze do ładowarek absolutnie dominowało w telefonach Nokii przed erą microUSB?", "answers": ["Mini-USB", "Szerokie złącze systemowe 'FastPort'", "Tzw. 'gruby bolec' (potem 'cienki bolec')", "Apple 30-pin"], "correct": 2},
  {"category": "MUZYKA PL", "question": "Co to za duet, który zdobył popularność hip-hopowymi balladami, wydając m.in. płytę 'Mezokracja'?", "answers": ["Liber i Doniu", "Jeden Osiem L", "Verba", "Mezo i Tabb"], "correct": 3},
  {"category": "INTERNET", "question": "Jak nazywała się aplikacja P2P, która była znana z pobierania muzyki (i mnóstwa wirusów Trojan) z ikonką fioletowej nuty w sieci FastTrack?", "answers": ["KaZaA", "LimeWire", "Ares Galaxy", "BearShare"], "correct": 0},
  {"category": "FILM", "question": "Kto wyreżyserował polską adaptację lektury szkolnej 'Zemsta' z 2002 roku, w której zagrali Gajos, Polański i Olbrychski?", "answers": ["Jerzy Hoffman", "Andrzej Wajda", "Krzysztof Zanussi", "Jan Jakub Kolski"], "correct": 1},
  {"category": "GRY", "question": "Jak nazywała się niezwykle popularna gra wyścigowa z otwartym miastem Bayview z 2004 roku?", "answers": ["NFS Underground 2", "Burnout 3", "Midnight Club 3", "Juiced"], "correct": 0},
  {"category": "TV PL", "question": "Jak nazywał się program TVN o zjawiskach paranormalnych i medycynie niekonwencjonalnej, emitowany z charakterystyczną mroczną muzyką?", "answers": ["Nie do wiary", "Mroczne sekrety", "Strefa 11", "Z archiwum X"], "correct": 0},
  {"category": "SERIALE PL", "question": "Jakie nazwisko panieńskie nosiła Halina Kiepska?", "answers": ["Kowal", "Norek", "Rozwadowska", "Bąk"], "correct": 2},
  {"category": "SKANDALE", "question": "Jaka dziennikarka i prezenterka zasłynęła wyśmianiem i krytykowaniem ubioru gwiazd w rubryce 'Moda Polska' w 'Show' / 'Fakcie', używając niezwykle kwiecistego języka?", "answers": ["Joanna Horodyńska", "Tomasz Jacyków", "Agnieszka Jastrzębska", "Karolina Korwin-Piotrowska (Magiel Towarzyski)"], "correct": 0},
  {"category": "SPORT", "question": "W którym roku odbyły się słynne Mistrzostwa Europy w Piłce Nożnej, gdzie wygrała 'defensywna' reprezentacja Grecji?", "answers": ["2000", "2004", "2008", "2012"], "correct": 1},
  {"category": "POLITYKA", "question": "Jaki pseudonim przylgnął do Zbigniewa Ziobry po słynnej sprawie kardiochirurga dr. G., kiedy powiedział, że 'już nikt nigdy przez tego pana życia pozbawiony nie będzie'?", "answers": ["Szeryf", "Ziobro-Zero", "Polski Giuliani", "Żelazny Prokurator"], "correct": 0},
  {"category": "TELEFONY", "question": "Jaka usługa wprowadzona do telefonów (w Polsce szerzej po 2006 r.) zwiastowała powolny koniec SMS-ów?", "answers": ["WhatsApp (później)", "Era Omnix", "Mobilne GG na Java (Mobile GG)", "Wideo-rozmowy 3G"], "correct": 2},
  {"category": "INTERNET PL", "question": "Jakim skrótem określało się pliki MP3 udostępniane masowo na serwisie Wrzuta.pl, które często miały dopiski '(HQ) (Bass Boosted)'?", "answers": [".wav", ".wma", "Nuta", "Audio.mp3"], "correct": 2},
  {"category": "MUZYKA PL", "question": "Kto śpiewał głośny na forach internetowych kawałek o imieniu z frazą 'Agnieszka już dawno tutaj nie mieszka' (choć jest on z '99, w 00' to był kult pod gitarę)?", "answers": ["Hey", "Lombard", "Łzy", "Chłopcy z Placu Broni"], "correct": 2},
  {"category": "TV PL", "question": "W którym z programów występował wczesny kabaret Mumio ze swoimi absurdalnymi reklamami sieci komórkowej (Plus)?", "answers": ["To były po prostu reklamy, ale Mumio stało się fenomenem", "W Szymon Majewski Show", "W Kuba Wojewódzki", "W Śmiechu warte"], "correct": 0},
  {"category": "GRY", "question": "Jaka darmowa, polska gra polegająca na skakaniu narciarzem kreskowym (wzorowana na DSJ, nazywana w kafejkach 'Skokami') biła rekordy popularności?", "answers": ["Deluxe Ski Jump 2 (DSJ 2 to fińska, ale u nas królowała)", "Ski Jumper 3D", "Małysz Jump", "Skoki Narciarskie 2002"], "correct": 0},
  {"category": "SERIALE PL", "question": "Jak miał na imię najmłodszy i często wykorzystywany intelektualnie przez rodzinę syn Kiepskich?", "answers": ["Waldek", "Cycu", "Boczek", "Piotrek"], "correct": 0},
  {"category": "SKANDALE", "question": "Kto z 'Big Brothera' wystąpił w 2001 r. w kontrowersyjnym filmie Jerzego Gruzy 'Gulczas, a jak myślisz?' u boku m.in. Janusza Rewińskiego?", "answers": ["Tylko Piotr Gulczyński", "Wszyscy główni uczestnicy pierwszej edycji", "Klaudiusz i Gulczas", "Manuela i Janusz Dzięcioł"], "correct": 1}
]
